CatLink/__init__.py
CatLink/client.py
CatLink/errors.py
CatLink/events.py
CatLink/models.py
CatLink/node.py
CatLink/player.py
CatLink/rest.py
CatLink/voice.py
CatLink/voice_client.py
CatLink/websocket.py
catlink-0.1.0.dist-info/METADATA
catlink-0.1.0.dist-info/WHEEL
catlink-0.1.0.dist-info/top_level.txt
catlink-0.1.0.dist-info/RECORD
