Metadata-Version: 2.4
Name: CatLink
Version: 0.1.0
Summary: A minimal, framework-agnostic Lavalink v3,4 client develope by kusanagi_akane
Requires-Python: >=3.9
Requires-Dist: aiohttp
Requires-Dist: websockets
